otcbtc_client/__init__.py
otcbtc_client/base.py
otcbtc_client/client.py
otcbtc_client/kline.py
otcbtc_client/market.py
otcbtc_client/order.py
otcbtc_client/order_book.py
otcbtc_client/ticker.py
otcbtc_client/timestamp.py
otcbtc_client/trade.py
otcbtc_client/user.py
otcbtc_client-0.2.1.dist-info/LICENSE
otcbtc_client-0.2.1.dist-info/METADATA
otcbtc_client-0.2.1.dist-info/WHEEL
otcbtc_client-0.2.1.dist-info/top_level.txt
otcbtc_client-0.2.1.dist-info/RECORD
